setup.py
hurler/__init__.py
hurler/callbacks.py
hurler/filters.py
hurler/test_callbacks.py
hurler/test_example.py
hurler/test_filters.py
hurler.egg-info/PKG-INFO
hurler.egg-info/SOURCES.txt
hurler.egg-info/dependency_links.txt
hurler.egg-info/top_level.txt