Metadata-Version: 1.1
Name: hurler
Version: 0.1.0
Summary: A simple callback mechanism with decorated filters.
Home-page: http://github.com/Wessie/hurler/
Author: Wesley Bitter
Author-email: hurler@wessie.info
License: BSD
Platform: UNKNOWN
Classifier: Development Status :: 4 - Beta
Classifier: Intended Audience :: Developers
Classifier: License :: OSI Approved :: BSD License
Classifier: Operating System :: OS Independent
Classifier: Programming Language :: Python
Classifier: Programming Language :: Python :: 2.7
Classifier: Programming Language :: Python :: 3.3
Classifier: Topic :: Software Development :: Libraries :: Python Modules
Classifier: Topic :: Utilities
